ibm_spectrum_discover_application_sdk/ApplicationLib.py
ibm_spectrum_discover_application_sdk/ApplicationMessageBase.py
ibm_spectrum_discover_application_sdk/DocumentRetrievalBase.py
ibm_spectrum_discover_application_sdk/__init__.py
ibm_spectrum_discover_application_sdk/util/__init__.py
ibm_spectrum_discover_application_sdk/util/aes_cipher.py
ibm_spectrum_discover_application_sdk-2.1.2.dist-info/LICENSE
ibm_spectrum_discover_application_sdk-2.1.2.dist-info/METADATA
ibm_spectrum_discover_application_sdk-2.1.2.dist-info/WHEEL
ibm_spectrum_discover_application_sdk-2.1.2.dist-info/top_level.txt
ibm_spectrum_discover_application_sdk-2.1.2.dist-info/RECORD
