Metadata-Version: 2.1
Name: ibm-spectrum-discover-application-sdk
Version: 2.1.2
Summary: IBM Spectrum Discover Application SDK
Home-page: https://github.com/IBM/Spectrum_Discover_Application_SDK
Author: Drew Olson
Author-email: drolson@us.ibm.com
Classifier: Programming Language :: Python :: 3
Classifier: License :: OSI Approved :: MIT License
Classifier: Operating System :: OS Independent
License-File: LICENSE
Requires-Dist: requests (==2.31.0)
Requires-Dist: confluent-kafka (==1.6.0)
Requires-Dist: cryptography (==41.0.2)
Requires-Dist: bcrypt (==3.1.7)
Requires-Dist: boto3 (==1.17.80)
Requires-Dist: pycryptodome (==3.9.9)
Requires-Dist: PyNaCl (==1.3.0)
Requires-Dist: paramiko (==2.10.1)
Requires-Dist: setuptools-rust (==1.6.0)
Requires-Dist: certifi (==2023.7.22)
